alumnium/__init__.py
alumnium/accessibility/__init__.py
alumnium/accessibility/accessibility_element.py
alumnium/accessibility/base_accessibility_tree.py
alumnium/accessibility/chromium_accessibility_tree.py
alumnium/accessibility/uiautomator2_accessibility_tree.py
alumnium/accessibility/xcuitest_accessibility_tree.py
alumnium/alumni.py
alumnium/area.py
alumnium/cache.py
alumnium/clients/__init__.py
alumnium/clients/http_client.py
alumnium/clients/native_client.py
alumnium/clients/typecasting.py
alumnium/drivers/__init__.py
alumnium/drivers/appium_driver.py
alumnium/drivers/base_driver.py
alumnium/drivers/keys.py
alumnium/drivers/playwright_async_driver.py
alumnium/drivers/playwright_driver.py
alumnium/drivers/scripts/waitFor.js
alumnium/drivers/scripts/waiter.js
alumnium/drivers/selenium_driver.py
alumnium/mcp/__init__.py
alumnium/mcp/drivers.py
alumnium/mcp/handlers.py
alumnium/mcp/screenshots.py
alumnium/mcp/server.py
alumnium/mcp/state.py
alumnium/mcp/tools.py
alumnium/result.py
alumnium/server/README.md
alumnium/server/__init__.py
alumnium/server/accessibility/__init__.py
alumnium/server/accessibility/base_server_accessibility_tree.py
alumnium/server/accessibility/server_chromium_accessibility_tree.py
alumnium/server/accessibility/server_uiautomator2_accessibility_tree.py
alumnium/server/accessibility/server_xcuitest_accessibility_tree.py
alumnium/server/agents/__init__.py
alumnium/server/agents/actor_agent.py
alumnium/server/agents/actor_prompts/anthropic/system.md
alumnium/server/agents/actor_prompts/anthropic/user.md
alumnium/server/agents/actor_prompts/deepseek/system.md
alumnium/server/agents/actor_prompts/deepseek/user.md
alumnium/server/agents/actor_prompts/google/system.md
alumnium/server/agents/actor_prompts/google/user.md
alumnium/server/agents/actor_prompts/meta/system.md
alumnium/server/agents/actor_prompts/meta/user.md
alumnium/server/agents/actor_prompts/mistralai/system.md
alumnium/server/agents/actor_prompts/mistralai/user.md
alumnium-0.17.0.dist-info/METADATA
alumnium-0.17.0.dist-info/WHEEL
alumnium-0.17.0.dist-info/entry_points.txt
alumnium-0.17.0.dist-info/RECORD
