Metadata-Version: 2.3
Name: alumnium
Version: 0.17.0
Summary: Pave the way towards AI-powered test automation.
License: MIT
Author: Alex Rodionov
Author-email: p0deje@gmail.com
Requires-Python: >=3.10,<4.0
Classifier: License :: OSI Approved :: MIT License
Classifier: Programming Language :: Python :: 3
Classifier: Programming Language :: Python :: 3.10
Classifier: Programming Language :: Python :: 3.11
Classifier: Programming Language :: Python :: 3.12
Classifier: Programming Language :: Python :: 3.13
Requires-Dist: appium-python-client (>=5.1.1,<6.0.0)
Requires-Dist: fastapi (>=0.127,<0.128)
Requires-Dist: langchain (>=1.1.0,<2.0.0)
Requires-Dist: langchain-anthropic (>=1.2.0,<2.0.0)
Requires-Dist: langchain-aws (>=1.1.0,<2.0.0)
Requires-Dist: langchain-deepseek (>=1.0.1,<2.0.0)
Requires-Dist: langchain-google-genai (>=4.2.0,<5.0.0)
Requires-Dist: langchain-mistralai (>=1.1.0,<2.0.0)
Requires-Dist: langchain-ollama (>=1.0.0,<2.0.0)
Requires-Dist: langchain-openai (>=1.1.0,<2.0.0)
Requires-Dist: langchain-xai (>=1.1.0,<2.0.0)
Requires-Dist: mcp (>=1.2.0,<2.0.0)
Requires-Dist: playwright (>=1.49,<2.0)
Requires-Dist: pydantic (>=2.10.0,<3.0.0)
Requires-Dist: retry2 (>=0.9,<0.10)
Requires-Dist: rich (>=14.0.0,<15.0.0)
Requires-Dist: selenium (>=4.0,<5.0)
Requires-Dist: sqlalchemy (>=2.0,<3.0)
Requires-Dist: xxhash (>=3.5.0,<4.0.0)
Project-URL: Homepage, https://alumnium.ai
Project-URL: Repository, https://github.com/alumnium-hq/alumnium
